{
    "2023-09-17 19:28:55.547044": {
        "username": "Max_Kryvytskyi",
        "message": "dasdw"
    },
    "2023-09-17 19:35:21.836501": {
        "username": "Max_Kryvytskyi",
        "message": "1212"
    },
    "2023-09-17 19:35:32.628357": {
        "username": "2131231",
        "message": "213123123"
    },
    "2023-09-17 19:35:38.917128": {
        "username": "23123123123",
        "message": "123123123"
    },
    "2023-09-17 19:36:23.852236": {
        "username": "MaxKryvytskyi",
        "message": "sa"
    },
    "2023-09-17 19:36:55.488468": {
        "username": "MaxKryvytskyi",
        "message": "docker"
    },
    "2023-09-17 19:44:56.981137": {
        "username": "1111",
        "message": "1111"
    },
    "2023-09-18 00:47:20.155143": {
        "username": "Max Kryvytskyi",
        "message": "1111111"
    },
    "2023-09-18 00:48:14.894814": {
        "username": "MaxKryvytskyi",
        "message": "123"
    },
    "2023-09-18 00:48:17.404648": {
        "username": "",
        "message": ""
    },
    "2023-09-18 00:48:48.617561": {
        "username": "MaxKryvytskyi",
        "message": "h"
    }
}